celloracle/__init__.py
celloracle/helpers.py
celloracle/version.py
celloracle/applications/__init__.py
celloracle/applications/development_module.py
celloracle/applications/differentiation_flow.py
celloracle/applications/pseudotime.py
celloracle/applications/scatter_to_grid.py
celloracle/applications/systematic_analysis_helper.py
celloracle/applications/utility.py
celloracle/data/__init__.py
celloracle/data/config.py
celloracle/data/load_data.py
celloracle/data/load_promoter_base_GRN.py
celloracle/data_conversion/__init__.py
celloracle/data_conversion/process_seurat_object.py
celloracle/data_conversion/seurat_to_mtx.R
celloracle/go_analysis/__init__.py
celloracle/go_analysis/goatools_wrapper.py
celloracle/go_analysis/data/biomart_xref.mm10.txt
celloracle/go_analysis/data/hg19_xref.txt
celloracle/motif_analysis/__init__.py
celloracle/motif_analysis/motif_analysis_utility.py
celloracle/motif_analysis/motif_data.py
celloracle/motif_analysis/process_bed_file.py
celloracle/motif_analysis/process_cicero_data.py
celloracle/motif_analysis/reference_genomes.py
celloracle/motif_analysis/tfinfo_core.py
celloracle/motif_analysis/tss_annotation.py
celloracle/motif_analysis/tss_ref_data/AmexG_v6.0-DD_tss_info.bed
celloracle/motif_analysis/tss_ref_data/Cavpor3.0_tss_info.bed
celloracle/motif_analysis/tss_ref_data/Sscrofa11.1_tss_info.bed
celloracle/motif_analysis/tss_ref_data/TAIR10_tss_info.bed
celloracle/motif_analysis/tss_ref_data/Xenopus_laevis_v10.1_tss_info.bed
celloracle/motif_analysis/tss_ref_data/ce10_tss_info.bed
celloracle/motif_analysis/tss_ref_data/ce6_tss_info.bed
celloracle/motif_analysis/tss_ref_data/danRer10_tss_info.bed
celloracle/motif_analysis/tss_ref_data/danRer11_tss_info.bed
celloracle/motif_analysis/tss_ref_data/danRer7_tss_info.bed
celloracle/motif_analysis/tss_ref_data/dm3_tss_info.bed
celloracle/motif_analysis/tss_ref_data/dm6_tss_info.bed
celloracle/motif_analysis/tss_ref_data/galGal4_tss_info.bed
celloracle-0.20.0.dist-info/LICENSE
celloracle-0.20.0.dist-info/METADATA
celloracle-0.20.0.dist-info/WHEEL
celloracle-0.20.0.dist-info/entry_points.txt
celloracle-0.20.0.dist-info/top_level.txt
celloracle-0.20.0.dist-info/RECORD
