Metadata-Version: 2.1
Name: celloracle
Version: 0.20.0
Summary: in silico gene perturbation analysis and GRN analysis with single cell data
Home-page: https://github.com/morris-lab/CellOracle
Author: Kenji Kamimoto
Author-email: kamimoto@wustl.edu
License: Apache License Version 2.0
Keywords: scRNA-seq,GRN,simulation,gene perturbation
Classifier: Development Status :: 4 - Beta
Classifier: Intended Audience :: Developers
Classifier: Topic :: Software Development :: Build Tools
Classifier: Programming Language :: Python :: 3.6
Classifier: Programming Language :: Python :: 3.7
Classifier: Programming Language :: Python :: 3.8
Classifier: Programming Language :: Python :: 3.10
Requires-Python: >=3.6
License-File: LICENSE
Requires-Dist: numpy ==1.26.4
Requires-Dist: scipy
Requires-Dist: cython
Requires-Dist: numba >=0.50.1
Requires-Dist: matplotlib <3.7
Requires-Dist: seaborn
Requires-Dist: scikit-learn
Requires-Dist: h5py >=3.1.0
Requires-Dist: pandas <=1.5.3,>=1.0.3
Requires-Dist: velocyto >=0.17
Requires-Dist: umap-learn
Requires-Dist: pyarrow >=0.17
Requires-Dist: tqdm >=4.45
Requires-Dist: igraph >=0.10.1
Requires-Dist: louvain
Requires-Dist: jupyter
Requires-Dist: anndata >=0.7.5
Requires-Dist: scanpy >=1.6
Requires-Dist: joblib
Requires-Dist: goatools
Requires-Dist: genomepy >=0.8.4
Requires-Dist: gimmemotifs <=0.17.2,>=0.14.4
Requires-Dist: anndata <=0.10.8
